# Timestamp in code: 2016-08-13 23:00:57
# Source code size mod 2**32: 292
# Method Name:       <module>
# Filename:          simple_source/bug36/01_fstring.py
# Argument count:    0
# Kw-only arguments: 0
# Number of locals:  0
# Stack size:        9
# Flags:             0x00000040 (NOFREE)
# Constants:
#    0: 0
#    1: None
#    2: 'Fred'
#    3: 50
#    4: 1991
#    5: 10
#    6: 12
#    7: ''
#    8: 'My name is '
#    9: ', my age next year is '
#   10: 1
#   11: ', my anniversary is '
#   12: '%A, %B %d, %Y'
#   13: '.'
#   14: 'He said his name is '
# Names:
#    0: datetime
#    1: name
#    2: age
#    3: date
#    4: anniversary
#    5: print
#    6: join
  3           0 LOAD_CONST               0 (0)
              2 LOAD_CONST               1 (None)
              4 IMPORT_NAME              0 (datetime)
              6 STORE_NAME               0 (datetime)

  4           8 LOAD_CONST               2 ('Fred')
             10 STORE_NAME               1 (name)

  5          12 LOAD_CONST               3 (50)
             14 STORE_NAME               2 (age)

  6          16 LOAD_NAME                0 (datetime)
             18 LOAD_ATTR                3 (date)
             20 LOAD_CONST               4 (1991)
             22 LOAD_CONST               5 (10)
             24 LOAD_CONST               6 (12)
             26 CALL_FUNCTION            3 (131 positional, 3 keyword pair)
             28 STORE_NAME               4 (anniversary)

  7          30 LOAD_NAME                5 (print)
             32 LOAD_CONST               7 ('')
             34 LOAD_ATTR                6 (join)
             36 LOAD_CONST               8 ('My name is ')
             38 LOAD_NAME                1 (name)
             40 FORMAT_VALUE             0
             42 LOAD_CONST               9 (', my age next year is ')
             44 LOAD_NAME                2 (age)
             46 LOAD_CONST              10 (1)
             48 BINARY_ADD
             50 FORMAT_VALUE             0
             52 LOAD_CONST              11 (', my anniversary is ')
             54 LOAD_NAME                4 (anniversary)
             56 LOAD_CONST              12 ('%A, %B %d, %Y')
             58 FORMAT_VALUE             4
             60 LOAD_CONST              13 ('.')
             62 BUILD_LIST               7
             64 CALL_FUNCTION            1 (131 positional, 1 keyword pair)
             66 CALL_FUNCTION            1 (131 positional, 1 keyword pair)
             68 POP_TOP

  8          70 LOAD_NAME                5 (print)
             72 LOAD_CONST               7 ('')
             74 LOAD_ATTR                6 (join)
             76 LOAD_CONST              14 ('He said his name is ')
             78 LOAD_NAME                1 (name)
             80 FORMAT_VALUE             2 (!r)
             82 LOAD_CONST              13 ('.')
             84 BUILD_LIST               3
             86 CALL_FUNCTION            1 (131 positional, 1 keyword pair)
             88 CALL_FUNCTION            1 (131 positional, 1 keyword pair)
             90 POP_TOP
             92 LOAD_CONST               1 (None)
             94 RETURN_VALUE

